mpipes/__init__.py
mpipes/__main__.py
mpipes/auth.py
mpipes/common.py
mpipes/common_auth.py
mpipes/files.py
mpipes/job.py
mpipes/logs.py
mpipes/main.py
mpipes/stats.py
mpipes/worker.py
micropipes_cli-0.6.dist-info/METADATA
micropipes_cli-0.6.dist-info/WHEEL
micropipes_cli-0.6.dist-info/entry_points.txt
micropipes_cli-0.6.dist-info/namespace_packages.txt
micropipes_cli-0.6.dist-info/top_level.txt
micropipes_cli-0.6.dist-info/RECORD
