Metadata-Version: 2.1
Name: micropipes-cli
Version: 0.6
Summary: Micropipes cli
Home-page: https://gitlab.com/aicu/lab/micropipes_cli
Author: Richard Holly
Author-email: rho@optimaideas.com
License: UNKNOWN
Platform: Any
Classifier: Programming Language :: Python :: 3
Classifier: Programming Language :: Python :: 3.6
Classifier: Intended Audience :: Developers
Classifier: Environment :: Console
Requires-Dist: cliff
Requires-Dist: certifi
Requires-Dist: urllib3
